timestep/__init__.py
timestep/agents/__init__.py
timestep/agents/gymnasium_agent/__init__.py
timestep/agents/gymnasium_agent/agent.py
timestep_agents_gymnasium_agent-0.1.0.dist-info/LICENSE
timestep_agents_gymnasium_agent-0.1.0.dist-info/METADATA
timestep_agents_gymnasium_agent-0.1.0.dist-info/WHEEL
timestep_agents_gymnasium_agent-0.1.0.dist-info/RECORD
