Metadata-Version: 2.1
Name: timestep-agents-gymnasium-agent
Version: 0.1.0
Summary: 
Author: Michael Schock
Author-email: m@mjschock.com
Requires-Python: >=3.9,<4.0
Classifier: Programming Language :: Python :: 3
Classifier: Programming Language :: Python :: 3.9
Classifier: Programming Language :: Python :: 3.10
Classifier: Programming Language :: Python :: 3.11
Requires-Dist: langchain (>=0.0.173,<0.0.174)
Requires-Dist: tenacity (>=8.2.2,<9.0.0)
